<?xml version="1.0"?>
<list xmlns:xsi="http://www.w3.org/2001/XMLSchema-instance" xsi:noNamespaceSchemaLocation="DropListData.xsd">
	<npc id="25149">
		<droplist>
			<category id="1" chance="56.8719">
				<item id="436" min="2" max="4" chance="29.4331"/>
				<item id="469" min="1" max="3" chance="70.5669"/>
			</category>
			<category id="2" chance="51.986">
				<item id="83" min="1" max="1" chance="10.2596"/>
				<item id="144" min="1" max="1" chance="10.2596"/>
				<item id="124" min="1" max="1" chance="7.6006"/>
				<item id="127" min="1" max="1" chance="7.6006"/>
				<item id="130" min="1" max="1" chance="7.6006"/>
				<item id="2026" min="3" max="9" chance="56.679"/>
			</category>
			<category id="3" chance="57.1224">
				<item id="6576" min="1" max="3" chance="100"/>
			</category>
		</droplist>
	</npc>
</list>