<?xml version="1.0" encoding="UTF-8"?><!DOCTYPE list SYSTEM "item.dtd">
<list>

  <armor id="14342" name="Necklace of Seal">
        <set name="enchantable" value="true"/>
        <set name="crystal_count" value="144"/>
        <set name="crystal_type" value="C"/>
        <set name="crystallizable" value="true"/>
        <set name="dropable" value="false"/>
        <set name="price" value="217200"/>
        <set name="sellable" value="true"/>
        <set name="tradeable" value="true"/>
        <set name="type" value="NONE"/>
        <set name="weight" value="150"/>
        <equip>
            <slot id="NECKLACE"/>
        </equip>
        <set name="ex_type" value="NECKLACE"/>
        <for>
            <add stat="mDef" order="0x10" value="64"/>
            <enchant stat="mDef" order="0x0C" value="0"/>
        </for>
    </armor>
	

    <armor id="14344" name="Ring of Seal">
       <set name="enchantable" value="true"/>
        <set name="crystal_count" value="72"/>
        <set name="crystal_type" value="C"/>
        <set name="crystallizable" value="true"/>
        <set name="dropable" value="false"/>
        <set name="price" value="108600"/>
        <set name="sellable" value="true"/>
        <set name="tradeable" value="true"/>
        <set name="type" value="NONE"/>
        <set name="weight" value="150"/>
        <equip>
            <slot id="RIGHT_FINGER"/>
            <slot id="LEFT_FINGER"/>
        </equip>
        <set name="ex_type" value="RING"/>
        <for>
            <add stat="mDef" order="0x10" value="32"/>
            <enchant stat="mDef" order="0x0C" value="0"/>
        </for>
    </armor>
	
	<armor id="14345" name="Black Ore Earring">
		<set name="icon" value="icon.accessary_earing_of_black_ore_i00"/>
		<set name="crystal_count" value="79"/>
        <set name="crystal_type" value="B"/>
        <set name="crystallizable" value="true"/>
        <set name="price" value="355500"/>
        <set name="type" value="NONE"/>
        <set name="weight" value="150"/>
        <equip>
            <slot id="RIGHT_EAR"/>
            <slot id="LEFT_EAR"/>
        </equip>
        <set name="ex_type" value="EARRING"/>
        <for>
            <add stat="mDef" order="0x10" value="54"/>
            <enchant stat="mDef" order="0x0C" value="0"/>
        </for>
	</armor>
	
	<armor id="14346" name="Black Ore Ring">
		<set name="icon" value="icon.accessary_ring_of_black_ore_i00"/>
		<set name="enchantable" value="true"/>
        <set name="crystal_count" value="52"/>
        <set name="crystal_type" value="B"/>
        <set name="crystallizable" value="true"/>
        <set name="dropable" value="false"/>
        <set name="price" value="237000"/>
        <set name="sellable" value="true"/>
        <set name="tradeable" value="true"/>
        <set name="type" value="NONE"/>
        <set name="weight" value="150"/>
        <equip>
            <slot id="RIGHT_FINGER"/>
            <slot id="LEFT_FINGER"/>
        </equip>
        <set name="ex_type" value="RING"/>
        <for>
            <add stat="mDef" order="0x10" value="36"/>
            <enchant stat="mDef" order="0x0C" value="0"/>
        </for>
	</armor>
	
	<armor id="14347" name="Black Ore Necklace">
		<set name="icon" value="icon.accessary_necklace_of_black_ore_i00"/>
		<set name="enchantable" value="true"/>
        <set name="crystal_count" value="105"/>
        <set name="crystal_type" value="B"/>
        <set name="crystallizable" value="true"/>
        <set name="dropable" value="false"/>
        <set name="price" value="474000"/>
        <set name="sellable" value="true"/>
        <set name="tradeable" value="true"/>
        <set name="type" value="NONE"/>
        <set name="weight" value="150"/>
        <equip>
            <slot id="NECKLACE"/>
        </equip>
        <set name="ex_type" value="NECKLACE"/>
        <for>
            <add stat="mDef" order="0x10" value="75"/>
            <enchant stat="mDef" order="0x0C" value="0"/>
        </for>
	</armor>
	
	
	
    <armor id="14348" name="Majestic Earring">
        <set name="crystal_count" value="79"/>
        <set name="crystal_type" value="A"/>
        <set name="crystallizable" value="true"/>
        <set name="price" value="749000"/>
        <set name="type" value="NONE"/>
        <set name="weight" value="150"/>
        <equip>
            <slot id="RIGHT_EAR"/>
            <slot id="LEFT_EAR"/>
        </equip>
        <set name="ex_type" value="EARRING"/>
        <for>
            <add stat="mDef" order="0x10" value="63"/>
			<add stat="maxMp" order="0x10" value="25"/>
            <enchant stat="mDef" order="0x0C" value="0"/>
        </for>
    </armor>
  
   <armor id="14349" name="Majestic Ring">
       <set name="enchantable" value="true"/>
        <set name="crystal_count" value="53"/>
        <set name="crystal_type" value="A"/>
        <set name="crystallizable" value="true"/>
        <set name="dropable" value="false"/>
        <set name="price" value="499500"/>
        <set name="sellable" value="true"/>
        <set name="tradeable" value="true"/>
        <set name="type" value="NONE"/>
        <set name="weight" value="150"/>
        <equip>
            <slot id="RIGHT_FINGER"/>
            <slot id="LEFT_FINGER"/>
        </equip>
        <set name="ex_type" value="RING"/>
        <for>
            <add stat="mDef" order="0x10" value="42"/>
			<add stat="maxMp" order="0x10" value="17"/>
            <enchant stat="mDef" order="0x0C" value="0"/>
        </for>
    </armor>
	

   <armor id="14350" name="Majestic Necklace">
        <set name="enchantable" value="true"/>
        <set name="crystal_count" value="106"/>
        <set name="crystal_type" value="A"/>
        <set name="crystallizable" value="true"/>
        <set name="dropable" value="false"/>
        <set name="price" value="999000"/>
        <set name="sellable" value="true"/>
        <set name="tradeable" value="true"/>
        <set name="type" value="NONE"/>
        <set name="weight" value="150"/>
        <equip>
            <slot id="NECKLACE"/>
        </equip>
        <set name="ex_type" value="NECKLACE"/>
        <for>
            <add stat="mDef" order="0x10" value="85"/>
			<add stat="maxMp" order="0x10" value="33"/>
            <enchant stat="mDef" order="0x0C" value="0"/>
        </for>
    </armor>
</list>
